{"6":{"headsign":"Chicago"},"7":{"headsign":"South Bend"},"8":{"headsign":"Chicago"},"9":{"headsign":"South Bend"},"11":{"headsign":"South Bend"},"12":{"headsign":"Chicago"},"13":{"headsign":"South Bend"},"14":{"headsign":"Chicago"},"15":{"headsign":"South Bend"},"17":{"headsign":"South Bend"},"18":{"headsign":"Chicago"},"19":{"headsign":"South Bend"},"20":{"headsign":"Chicago"},"22":{"headsign":"Chicago"},"25":{"headsign":"South Bend"},"28":{"headsign":"Chicago"},"29":{"headsign":"South Bend"},"30":{"headsign":"Chicago"},"31":{"headsign":"South Bend"},"101":{"headsign":"Carroll Ave. (Michigan City)"},"102":{"headsign":"Chicago"},"103":{"headsign":"Carroll Ave. (Michigan City)"},"104":{"headsign":"Chicago"},"105":{"headsign":"Carroll Ave. (Michigan City)"},"106":{"headsign":"Chicago"},"108":{"headsign":"Chicago"},"109":{"headsign":"Carroll Ave. (Michigan City)"},"110":{"headsign":"Chicago"},"111":{"headsign":"Carroll Ave. (Michigan City)"},"112":{"headsign":"Chicago"},"113":{"headsign":"Carroll Ave. (Michigan City)"},"114":{"headsign":"Chicago"},"115":{"headsign":"Carroll Ave. (Michigan City)"},"117":{"headsign":"Carroll Ave. (Michigan City)"},"118":{"headsign":"Chicago"},"119":{"headsign":"Carroll Ave. (Michigan City)"},"120":{"headsign":"Chicago"},"121":{"headsign":"Carroll Ave. (Michigan City)"},"122":{"headsign":"Chicago"},"123":{"headsign":"Carroll Ave. (Michigan City)"},"124":{"headsign":"Chicago"},"126":{"headsign":"Chicago"},"127":{"headsign":"Carroll Ave. (Michigan City)"},"128":{"headsign":"Chicago"},"129":{"headsign":"Carroll Ave. (Michigan City)"},"130":{"headsign":"Chicago"},"131":{"headsign":"Carroll Ave. (Michigan City)"},"132":{"headsign":"Chicago"},"133":{"headsign":"Carroll Ave. (Michigan City)"},"135":{"headsign":"Carroll Ave. (Michigan City)"},"201":{"headsign":"Miller"},"203":{"headsign":"Miller"},"205":{"headsign":"Miller"},"207":{"headsign":"Miller"},"209":{"headsign":"Miller"},"210":{"headsign":"Chicago"},"212":{"headsign":"Chicago"},"214":{"headsign":"Chicago"},"215":{"headsign":"Miller"},"216":{"headsign":"Chicago"},"218":{"headsign":"Chicago"},"220":{"headsign":"Chicago"},"222":{"headsign":"Chicago"},"224":{"headsign":"Chicago"},"225":{"headsign":"Miller"},"226":{"headsign":"Chicago"},"228":{"headsign":"Chicago"},"401":{"headsign":"South Bend"},"403":{"headsign":"South Bend"},"405":{"headsign":"South Bend"},"422":{"headsign":"Carroll Ave. (Michigan City)"},"424":{"headsign":"Carroll Ave. (Michigan City)"},"426":{"headsign":"Carroll Ave. (Michigan City)"},"428":{"headsign":"Carroll Ave. (Michigan City)"},"430":{"headsign":"Carroll Ave. (Michigan City)"},"432":{"headsign":"Carroll Ave. (Michigan City)"},"502":{"headsign":"Chicago"},"503":{"headsign":"South Bend"},"504":{"headsign":"Chicago"},"505":{"headsign":"South Bend"},"506":{"headsign":"Chicago"},"507":{"headsign":"South Bend"},"508":{"headsign":"Chicago"},"509":{"headsign":"South Bend"},"510":{"headsign":"Chicago"},"511":{"headsign":"South Bend"},"600":{"headsign":"Chicago"},"601":{"headsign":"Carroll Ave. (Michigan City)"},"603":{"headsign":"Carroll Ave. (Michigan City)"},"605":{"headsign":"Carroll Ave. (Michigan City)"},"606":{"headsign":"Chicago"},"608":{"headsign":"Chicago"},"610":{"headsign":"Chicago"},"613":{"headsign":"Carroll Ave. (Michigan City)"},"701":{"headsign":"South Bend"},"703":{"headsign":"South Bend"}}