{"133937":{"stopID":"133937","stopName":"Millard","stopLat":41.79722,"stopLon":-72.71466},"133938":{"stopID":"133938","stopName":"HPAC","stopLat":41.78582,"stopLon":-72.70316},"133939":{"stopID":"133939","stopName":"Girard/Asylum","stopLat":41.77531,"stopLon":-72.70784},"133940":{"stopID":"133940","stopName":"University Commons","stopLat":41.80053,"stopLon":-72.71696},"133941":{"stopID":"133941","stopName":"Bishop's Corner (Marshall's)","stopLat":41.78432,"stopLon":-72.74764},"133942":{"stopID":"133942","stopName":"Blue Back Square E","stopLat":41.76073,"stopLon":-72.74227},"133943":{"stopID":"133943","stopName":"Art Store","stopLat":41.73212,"stopLon":-72.7311},"133944":{"stopID":"133944","stopName":"West Farms Mall (Macy's)","stopLat":41.72537,"stopLon":-72.76137},"133945":{"stopID":"133945","stopName":"Parkville Market","stopLat":41.75832,"stopLon":-72.70147},"133946":{"stopID":"133946","stopName":"Blue Back Square W","stopLat":41.76061,"stopLon":-72.7419}}