{"135289":{"stopID":"135289","stopName":"Alfond Commons","stopLat":44.55078,"stopLon":-69.63104},"135290":{"stopID":"135290","stopName":"Diamond","stopLat":44.56266,"stopLon":-69.659},"135291":{"stopID":"135291","stopName":"Davis","stopLat":44.56449,"stopLon":-69.66009},"135292":{"stopID":"135292","stopName":"Cotter Drive","stopLat":44.56301,"stopLon":-69.66053},"135293":{"stopID":"135293","stopName":"Pugh Center","stopLat":44.563,"stopLon":-69.66207},"135294":{"stopID":"135294","stopName":"Seton Off Campus Parking Lot","stopLat":44.5491,"stopLon":-69.65747},"135295":{"stopID":"135295","stopName":"Oxford St. off campus parking lot","stopLat":44.54722,"stopLon":-69.63021},"135296":{"stopID":"135296","stopName":"Lockwood Hotel","stopLat":44.54886,"stopLon":-69.62847},"135297":{"stopID":"135297","stopName":"Head of Falls","stopLat":44.55128,"stopLon":-69.62804},"135298":{"stopID":"135298","stopName":"Social Security Office","stopLat":44.55771,"stopLon":-69.62744},"135299":{"stopID":"135299","stopName":"Greene Block Drop Off","stopLat":44.54904,"stopLon":-69.63034},"135300":{"stopID":"135300","stopName":"West and Gilman Streets","stopLat":44.55374,"stopLon":-69.63745},"135301":{"stopID":"135301","stopName":"Burleigh and Gilman Streets","stopLat":44.55383,"stopLon":-69.63907},"135302":{"stopID":"135302","stopName":"Mount Merici Ave and Mayflower Hill","stopLat":44.55656,"stopLon":-69.65596},"135303":{"stopID":"135303","stopName":"HAARC-Main Entrance","stopLat":44.56681,"stopLon":-69.66372},"135304":{"stopID":"135304","stopName":"HAARC-Team Entrance","stopLat":44.56834,"stopLon":-69.6634},"135305":{"stopID":"135305","stopName":"Walmart","stopLat":44.56853,"stopLon":-69.6455},"135306":{"stopID":"135306","stopName":"Flagship Theaters","stopLat":44.54516,"stopLon":-69.66467},"141950":{"stopID":"141950","stopName":"Jitney Demand Stop","stopLat":44.56573,"stopLon":-69.6617},"154595":{"stopID":"154595","stopName":"MaineGeneral","stopLat":44.56558,"stopLon":-69.64594}}